{
  "type": "FeatureCollection",
  "features": [{
    "type": "Feature",
    "properties": {
      "id": 1,
      "name": "LA COULEE VERTE",
      "message": "Lorem ipsum dolor sit amet, consectetur adipisicing elit."
    },
    "geometry": {
      "type": "Polygon",
      "coordinates": [
        [
          [2.33143, 48.94202],
          [2.33125, 48.94196],
          [2.33101, 48.94197],
          [2.33056, 48.94209],
          [2.33031, 48.94193],
          [2.32895, 48.94147],
          [2.32716, 48.94087],
          [2.32719, 48.94064],
          [2.32611, 48.94033],
          [2.32511, 48.94015],
          [2.32465, 48.94026],
          [2.32425, 48.94054],
          [2.32371, 48.94115],
          [2.32309, 48.94092],
          [2.32391, 48.94015],
          [2.32519, 48.93981],
          [2.32613, 48.94009],
          [2.32742, 48.94034],
          [2.32761, 48.94035],
          [2.32767, 48.94033],
          [2.3288, 48.94079],
          [2.32929, 48.94084],
          [2.32929, 48.941],
          [2.32939, 48.94104],
          [2.33073, 48.94154],
          [2.33073, 48.94155],
          [2.3308, 48.9416],
          [2.33108, 48.94141],
          [2.33115, 48.94135],
          [2.33224, 48.94197],
          [2.33246, 48.9421],
          [2.33268, 48.94221],
          [2.33255, 48.9423],
          [2.3317, 48.94279],
          [2.33144, 48.94263],
          [2.33156, 48.94255],
          [2.3317, 48.94237],
          [2.33171, 48.94228],
          [2.33169, 48.9422],
          [2.33153, 48.94207],
          [2.33149, 48.94204]
        ]
      ]
    }
  }, {
    "type": "Feature",
    "properties": {
      "SITEID": 2,
      "NOM": "VERDUN-EMMAÜS",
      "message": "Lorem ipsum dolor sit amet, consectetur adipisicing elit."
    },
    "geometry": {
      "type": "Polygon",
      "coordinates": [
        [
          [2.33292,48.93476],
          [2.33301,48.9354],
          [2.33506,48.93554],
          [2.33507,48.93531],
          [2.33319,48.93518],
          [2.33312,48.93475]
        ]
      ]
    }
  }, {
    "type": "Feature",
    "properties": {
      "SITEID": 3,
      "NOM": "VERDUN",
      "message": "Lorem ipsum dolor sit amet, consectetur adipisicing elit."
    },
    "geometry": {
      "type": "Polygon",
      "coordinates": [
        [
          [2.32284,48.93476],
          [2.32283,48.93487],
          [2.32476,48.935],
          [2.32478,48.9349]
        ]
      ]
    }
  }, {
    "type": "Feature",
    "properties": {
      "SITEID": 4,
      "NOM": "ALLEE DU CHEMIN VERT",
      "message": "Lorem ipsum dolor sit amet, consectetur adipisicing elit."
    },
    "geometry": {
      "type": "Polygon",
      "coordinates": [
        [
          [2.33302,48.93768],
          [2.33292,48.93768],
          [2.33289,48.93769],
          [2.33287,48.93772],
          [2.33289,48.93773],
          [2.3329,48.93774],
          [2.33289,48.93776],
          [2.33292,48.93776],
          [2.33292,48.93774],
          [2.33292,48.93772],
          [2.33294,48.93771],
          [2.33303,48.93771],
          [2.33307,48.9377],
          [2.33308,48.93768],
          [2.33308,48.93767],
          [2.33296,48.93695],
          [2.33295,48.9369],
          [2.33324,48.93688],
          [2.33342,48.9368],
          [2.33341,48.93668],
          [2.33401,48.93667],
          [2.334,48.93628],
          [2.33374,48.93629],
          [2.3334,48.93629],
          [2.33337,48.93616],
          [2.33347,48.93615],
          [2.33381,48.93612],
          [2.33412,48.93612],
          [2.33414,48.93616],
          [2.33417,48.93641],
          [2.33419,48.93663],
          [2.33418,48.93667],
          [2.33417,48.93668],
          [2.33416,48.9367],
          [2.33413,48.9367],
          [2.33404,48.9367],
          [2.33395,48.93671],
          [2.3337,48.93676],
          [2.33358,48.93681],
          [2.33341,48.93692],
          [2.33332,48.937],
          [2.33327,48.93709],
          [2.33324,48.93716],
          [2.33323,48.93728],
          [2.33324,48.93735],
          [2.33326,48.93742],
          [2.33329,48.93748],
          [2.33334,48.93755],
          [2.33339,48.93759],
          [2.33341,48.93762],
          [2.33345,48.93765],
          [2.33346,48.93766],
          [2.33342,48.93769],
          [2.33321,48.93775],
          [2.3331,48.93777],
          [2.33295,48.93778],
          [2.33285,48.93779],
          [2.33275,48.9378],
          [2.33264,48.9378],
          [2.33263,48.93777],
          [2.33281,48.93776],
          [2.3328,48.93773],
          [2.33279,48.93767],
          [2.33287,48.93765],
          [2.33278,48.93704],
          [2.3327,48.93635],
          [2.33275,48.93633],
          [2.33281,48.93686],
          [2.33283,48.93694],
          [2.33291,48.93696],
          [2.33303,48.93762]
        ]
      ]
    }
  }, {
    "type": "Feature",
    "properties": {
      "SITEID": 5,
      "NOM": "MADAME DE NANTEUIL",
      "message": "Lorem ipsum dolor sit amet, consectetur adipisicing elit."
    },
    "geometry": {
      "type": "Polygon",
      "coordinates": [
        [
          [2.329338, 48.942510],
          [2.329029, 48.942711],
          [2.328967, 48.942711],
          [2.328975, 48.942739],
          [2.329045, 48.942751],
          [2.329088, 48.942751],
          [2.329330, 48.943058],
          [2.329716, 48.943175],
          [2.330523, 48.943411],
          [2.330995, 48.943240],
          [2.329493, 48.942375],
          [2.329348, 48.942505]
        ]
      ]
    }
  }, {
    "type": "Feature",
    "properties": {
      "SITEID": 6,
      "NOM": "DE GAULE-LECLERC",
      "message": "Lorem ipsum dolor sit amet, consectetur adipisicing elit."
    },
    "geometry": {
      "type": "Polygon",
      "coordinates": [
        [
          [2.31836,48.94263],
          [2.31845,48.9427],
          [2.31847,48.94274],
          [2.31848,48.94279],
          [2.31848,48.94284],
          [2.31873,48.9428],
          [2.31973,48.94257],
          [2.32038,48.94232],
          [2.32098,48.94202],
          [2.32211,48.94138],
          [2.322,48.94136],
          [2.32191,48.94131],
          [2.32189,48.94122],
          [2.32189,48.94114],
          [2.32201,48.94104],
          [2.32205,48.94101],
          [2.32207,48.94101],
          [2.32212,48.941],
          [2.32226,48.94102],
          [2.32231,48.94103],
          [2.32246,48.94116],
          [2.3234,48.94068],
          [2.32389,48.94022],
          [2.32437,48.94009],
          [2.32507,48.93977],
          [2.32512,48.93975],
          [2.32504,48.93971],
          [2.32416,48.93959],
          [2.32418,48.93931],
          [2.32378,48.93929],
          [2.32363,48.94009],
          [2.32347,48.9403],
          [2.32315,48.94055],
          [2.32227,48.94099],
          [2.3222,48.94101],
          [2.32212,48.941],
          [2.32204,48.94101],
          [2.32196,48.94107],
          [2.3219,48.94111],
          [2.32188,48.94113],
          [2.32187,48.94117],
          [2.32184,48.94119],
          [2.32102,48.94163],
          [2.32043,48.94194],
          [2.31982,48.94221],
          [2.31922,48.94241]
        ]
      ]
    }
  }, {
    "type": "Feature",
    "properties": {
      "SITEID": 7,
      "NOM": "MOULIN DE CAGE",
      "message": "Lorem ipsum dolor sit amet, consectetur adipisicing elit."
    },
    "geometry": {
      "type": "Polygon",
      "coordinates": [
        [
          [2.32821,48.92354],
          [2.32797,48.92342],
          [2.32776,48.92342],
          [2.32769,48.92347],
          [2.32797,48.92355],
          [2.32849,48.924],
          [2.33002,48.92536],
          [2.3312,48.92681],
          [2.33131,48.92678],
          [2.33071,48.92596],
          [2.32997,48.92513]
        ]
      ]
    }
  }, {
    "type": "Feature",
    "properties": {
      "SITEID": 8,
      "NOM": "jEAN jAURES",
      "message": "Lorem ipsum dolor sit amet, consectetur adipisicing elit."
    },
    "geometry": {
      "type":"MultiPolygon",
      "coordinates":
      [
        [
          [
            [2.325475, 48.932037],
            [2.325572, 48.932079],
            [2.325658, 48.932058],
            [2.325797, 48.932051],
            [2.325840, 48.931952],
            [2.325926, 48.931614],
            [2.326151, 48.930676],
            [2.325851, 48.930641],
            [2.325658, 48.931543],
            [2.325593, 48.931889],
            [2.325550, 48.931966],
            [2.325497, 48.932008],
            [2.325475, 48.932022]
          ]
        ]
      ]
    }
  }, {
    "type": "Feature",
    "properties": {
      "SITEID": 9,
      "NOM": "VOIE PROMENADE SUD-CENTRE)",
      "message": "Lorem ipsum dolor sit amet, consectetur adipisicing elit."
    },
    "geometry": {
      "type":"MultiPolygon",
      "coordinates":
      [
        [
          [
            [2.329252, 48.932981],
            [2.329456, 48.932991],
            [2.330212, 48.929448],
            [2.329853, 48.929527],
            [2.329794, 48.929557],
            [2.329488, 48.931272],
            [2.329241, 48.932976]
          ]
        ],
        [
          [
            [2.328705, 48.935055],
            [2.329118, 48.933455],
            [2.329327, 48.933445],
            [2.329102, 48.934397],
            [2.329021, 48.934915],
            [2.328973, 48.935025],
            [2.328876, 48.935080],
            [2.328721, 48.935055]
          ]
        ]
      ]
    }
  }, {
    "type": "Feature",
    "properties": {
      "SITEID": 10,
      "NOM": "VOIE PROMENADE NORD",
      "message": "Lorem ipsum dolor sit amet, consectetur adipisicing elit."
    },
    "geometry": {
      "type": "Polygon",
      "coordinates": [
        [
          [2.32885,48.93562],
          [2.32874,48.93561],
          [2.32822,48.93776],
          [2.32819,48.93792],
          [2.32816,48.93807],
          [2.32821,48.93805],
          [2.32823,48.93805],
          [2.32822,48.93805],
          [2.32829,48.93802],
          [2.32837,48.93796],
          [2.3284,48.93776]
        ]
      ]
    }
  }, {
    "type": "Feature",
    "properties": {
      "SITEID": 11,
      "NOM": "ABBE PIERRE-NORMANDIE",
      "message": "Lorem ipsum dolor sit amet, consectetur adipisicing elit."
    },
    "geometry": {
      "type": "Polygon",
      "coordinates": [
        [
          [2.32931,48.93388],
          [2.32937,48.93343],
          [2.32944,48.93316],
          [2.33003,48.93314],
          [2.33101,48.93314],
          [2.33113,48.93358],
          [2.33123,48.93404],
          [2.33051,48.93397]
        ]
      ]
    }
  }, {
    "type": "Feature",
    "properties": {
      "SITEID": 12,
      "NOM": "FOND DE LA NOUE",
      "message": "Lorem ipsum dolor sit amet, consectetur adipisicing elit."
    },
    "geometry": {
      "type": "Polygon",
      "coordinates": [
        [
          [2.33209,48.93104],
          [2.33197,48.93095],
          [2.33161,48.93123],
          [2.33118,48.93175],
          [2.33074,48.93212],
          [2.33012,48.9326],
          [2.32972,48.9329],
          [2.32929,48.93301],
          [2.32943,48.93307],
          [2.3298,48.933],
          [2.33084,48.93223],
          [2.33135,48.93177],
          [2.33186,48.93117],
          [2.33195,48.9311]
        ]
      ]
    }
  }, {
    "type": "Feature",
    "properties": {
      "SITEID": 13,
      "NOM": "BOULEVARD GALLIENI",
      "message": "Lorem ipsum dolor sit amet, consectetur adipisicing elit."
    },
    "geometry": {
      "type": "Polygon",
      "coordinates": [
        [
        [  2.33165,48.92838],
          [2.33137,48.92857],
          [2.33163,48.9292],
          [2.33175,48.92939],
          [2.33208,48.93099],
          [2.33223,48.93097],
          [2.33197,48.92947],
          [2.33197,48.9291],
          [2.33193,48.92894]
        ]
      ]
    }
  }, {
    "type": "Feature",
    "properties": {
      "SITEID": 14,
      "NOM": "AUGUSTIN",
      "message": "Lorem ipsum dolor sit amet, consectetur adipisicing elit."
    },
    "geometry": {
      "type": "Polygon",
      "coordinates": [
        [
          [2.33261,48.92788],
          [2.33287,48.92775],
          [2.33321,48.92814],
          [2.33334,48.92838],
          [2.33349,48.92852],
          [2.33364,48.92884],
          [2.33337,48.9288],
          [2.33324,48.92885],
          [2.33308,48.92884],
          [2.33292,48.9289],
          [2.33277,48.92896],
          [2.33279,48.92899],
          [2.33288,48.92911],
          [2.33293,48.9292],
          [2.33297,48.9295],
          [2.33294,48.92977],
          [2.33302,48.92985],
          [2.33321,48.92985],
          [2.3332,48.92973],
          [2.33361,48.9297],
          [2.33366,48.9299],
          [2.33313,48.92996],
          [2.33331,48.93046],
          [2.33317,48.93047],
          [2.33312,48.93022],
          [2.33302,48.92996],
          [2.33288,48.92981],
          [2.33286,48.92932],
          [2.33285,48.9292],
          [2.33277,48.92909],
          [2.33244,48.92912],
          [2.33242,48.92909],
          [2.33222,48.92911],
          [2.33223,48.92915],
          [2.33202,48.92917],
          [2.33199,48.92909],
          [2.3319,48.92883],
          [2.33165,48.92837],
          [2.33197,48.92816],
          [2.33201,48.92838],
          [2.33214,48.92859],
          [2.33223,48.9287],
          [2.33237,48.92875],
          [2.3325,48.92878],
          [2.33267,48.92878],
          [2.33292,48.92873],
          [2.33307,48.9286],
          [2.33313,48.92846],
          [2.33305,48.92825],
          [2.33282,48.92805]
        ]
      ]
    }
  }, {
    "type": "Feature",
    "properties": {
      "SITEID": 15,
      "NOM": "HAUT DE LA NOUE",
      "message": "Lorem ipsum dolor sit amet, consectetur adipisicing elit."
    },
    "geometry": {
      "type": "Polygon",
      "coordinates": [
        [
          [2.326838, 48.930240],
          [2.327122, 48.930185],
          [2.327326, 48.930609],
          [2.327374, 48.930754],
          [2.327428, 48.931182],
          [2.327455, 48.931641],
          [2.327401, 48.931990],
          [2.327363, 48.932244],
          [2.327331, 48.932543],
          [2.327288, 48.932842],
          [2.327192, 48.933350],
          [2.326983, 48.934232],
          [2.326854, 48.934412],
          [2.326645, 48.934810],
          [2.326425, 48.934815],
          [2.326441, 48.934781],
          [2.326570, 48.934611],
          [2.326661, 48.934447],
          [2.326693, 48.934377],
          [2.326741, 48.934257],
          [2.326779, 48.934187],
          [2.326950, 48.933545],
          [2.327106, 48.932667],
          [2.327197, 48.932019],
          [2.327235, 48.931720],
          [2.327149, 48.930943],
          [2.327117, 48.930744],
          [2.327052, 48.930604],
          [2.326993, 48.930499],
          [2.326945, 48.930410],
          [2.326843, 48.930250]
        ]
      ]
    }
  }, {
    "type": "Feature",
    "properties": {
      "SITEID": 16,
      "NOM": "SQUARE RUE PASTEUR",
      "message": "Lorem ipsum dolor sit amet, consectetur adipisicing elit."
    },
    "geometry": {
      "type": "Polygon",
      "coordinates": [
        [
          [2.32792,48.92997],
          [2.32788,48.93032],
          [2.32766,48.93143],
          [2.32757,48.93142],
          [2.32737,48.93144],
          [2.32733,48.93098],
          [2.32729,48.93076],
          [2.32724,48.93055],
          [2.32737,48.93052],
          [2.32742,48.93048],
          [2.32746,48.93045],
          [2.32753,48.93041],
          [2.32756,48.93041],
          [2.32762,48.93038],
          [2.32769,48.93002]
        ]
      ]
    }
  }, {
    "type": "Feature",
    "properties": {
      "SITEID": 17,
      "NOM": "MAIL ROGER PREVOT",
      "message": "Lorem ipsum dolor sit amet, consectetur adipisicing elit."
    },
    "geometry": {
      "type": "Polygon",
      "coordinates": [
        [
          [2.32766,48.94102],
          [2.32702,48.94089],
          [2.32631,48.94169],
          [2.32602,48.94222],
          [2.32661,48.94225],
          [2.32678,48.94225],
          [2.3268,48.94228],
          [2.32681,48.94233],
          [2.32684,48.94238],
          [2.32693,48.94261],
          [2.32708,48.94287],
          [2.3272,48.94307],
          [2.32735,48.94338],
          [2.32741,48.94337],
          [2.32755,48.94363],
          [2.3277,48.94389],
          [2.32787,48.94421],
          [2.32803,48.94454],
          [2.32813,48.94451],
          [2.32804,48.94434],
          [2.3278,48.94388],
          [2.32757,48.94342],
          [2.32748,48.94322],
          [2.3274,48.94304],
          [2.32723,48.94272],
          [2.3271,48.94245],
          [2.32705,48.94235],
          [2.32704,48.94226],
          [2.32704,48.94227],
          [2.32692,48.94177],
          [2.32681,48.94171],
          [2.32674,48.9416],
          [2.32684,48.9415],
          [2.32714,48.94123],
          [2.32753,48.94127],
          [2.32753,48.94127]
        ]
      ]
    }
  }, {
    "type": "Feature",
    "properties": {
      "SITEID": 18,
      "NOM": "PONANT-PAUL SIGNAC",
      "message": "Lorem ipsum dolor sit amet, consectetur adipisicing elit."
    },
    "geometry": {
      "type":"MultiPolygon",
      "coordinates":
      [
        [
          [
            [2.32468,48.94204],
            [2.32461,48.94307],
            [2.32508,48.94389],
            [2.32603,48.94366],
            [2.32742,48.94329],
            [2.32795,48.94318],
            [2.328,48.94317],
            [2.32808,48.94317],
            [2.32815,48.9432],
            [2.32847,48.94377],
            [2.32841,48.94379],
            [2.32806,48.94321],
            [2.32799,48.94321],
            [2.32759,48.94332],
            [2.32689,48.9435],
            [2.32603,48.94371],
            [2.32514,48.94395],
            [2.32525,48.94403],
            [2.32543,48.94412],
            [2.32588,48.94426],
            [2.32635,48.94428],
            [2.32696,48.94422],
            [2.32779,48.94401],
            [2.32839,48.94381],
            [2.32913,48.94342],
            [2.3296,48.94338],
            [2.32964,48.94339],
            [2.32985,48.94306],
            [2.32993,48.94309],
            [2.32975,48.94339],
            [2.32964,48.94346],
            [2.32958,48.94348],
            [2.32958,48.94348],
            [2.32967,48.94359],
            [2.32981,48.94354],
            [2.32991,48.94345],
            [2.32997,48.94336],
            [2.33005,48.94339],
            [2.32995,48.94352],
            [2.32971,48.94363],
            [2.32972,48.94416],
            [2.32961,48.94419],
            [2.32962,48.94362],
            [2.32954,48.94355],
            [2.32948,48.94347],
            [2.32934,48.94349],
            [2.32918,48.94349],
            [2.32866,48.94376],
            [2.32807,48.94401],
            [2.32757,48.94416],
            [2.32704,48.94428],
            [2.32637,48.94434],
            [2.32587,48.94434],
            [2.32566,48.94428],
            [2.32526,48.94413],
            [2.32506,48.944],
            [2.32499,48.94393],
            [2.3245,48.94308],
            [2.32455,48.94236],
            [2.32455,48.94209],
            [2.32356,48.94205],
            [2.32352,48.94198],
            [2.32404,48.94198]
          ]
        ]
      ]
    }
  }, {
    "type": "Feature",
    "properties": {
      "SITEID": 19,
      "NOM": "FOSSE AUX ASTRES",
      "message": "Lorem ipsum dolor sit amet, consectetur adipisicing elit."
    },
    "geometry": {
      "type": "Polygon",
      "coordinates": [
        [
          [2.33116,48.94135],
          [2.3312,48.94131],
          [2.33184,48.94167],
          [2.33225,48.94189],
          [2.33221,48.94194],
          [2.3318,48.94171]
        ]
      ]
    }
  }, {
    "type": "Feature",
    "properties": {
      "SITEID": 20,
      "NOM": "SQUARE SAINTE MARIE",
      "message": "Lorem ipsum dolor sit amet, consectetur adipisicing elit."
    },
    "geometry": {
      "type":"MultiPolygon",
      "coordinates":
      [
        [
          [
            [2.33256,48.93886],
            [2.33281,48.93889],
            [2.33278,48.93867],
            [2.33277,48.93856],
            [2.33278,48.93856]
          ]
        ]
      ]
    }
  },  {
    "type": "Feature",
    "properties": {
      "SITEID": 21,
      "NOM": "CIMETIERES",
      "message": "Lorem ipsum dolor sit amet, consectetur adipisicing elit."
    },
    "geometry": {
      "type":"Polygon",
      "coordinates":
      [
        [
          [2.326143, 48.935042],
          [2.325089, 48.934950],
          [2.324826, 48.935476],
          [2.324722, 48.936039],
          [2.325263, 48.936221],
          [2.325360, 48.936258],
          [2.326296, 48.935067],
          [2.326148, 48.935042]
        ]
      ]
    }
  }, {
    "type": "Feature",
    "properties": {
      "SITEID": 22,
      "NOM": "CIMETIERES",
      "message": "Lorem ipsum dolor sit amet, consectetur adipisicing elit."
    },
    "geometry": {
        "type": "Polygon",
      "coordinates":
      [
        [
          [2.324247, 48.937372],
          [2.321629, 48.937118],
          [2.321817, 48.936046],
          [2.321844, 48.936016],
          [2.321897, 48.935987],
          [2.321945, 48.935942],
          [2.321999, 48.935932],
          [2.322112, 48.935937],
          [2.324467, 48.936156],
          [2.324488, 48.936171],
          [2.324252, 48.937377]
        ]
      ]
      }
  }, {
    "type": "Feature",
    "properties": {
      "SITEID": 23,
      "NOM": "NELSON MANDELA",
      "message": "Lorem ipsum dolor sit amet, consectetur adipisicing elit."
    },
    "geometry": {
      "type": "Polygon",
      "coordinates":
      [
        [
          [2.326993, 48.930131],
          [2.327068, 48.930205],
          [2.327111, 48.930235],
          [2.327819, 48.930061],
          [2.331634, 48.929179],
          [2.331617, 48.929099],
          [2.331596, 48.929084],
          [2.330207, 48.929403],
          [2.326988, 48.930121]
        ]
      ]
    }
  }, {
    "type": "Feature",
    "properties": {
      "SITEID": 24,
      "NOM": "CHEMIN DES RENIERS",
      "message": "Lorem ipsum dolor sit amet, consectetur adipisicing elit."
    },
    "geometry": {
      "type": "Polygon",
      "coordinates": [
        [
          [2.322798, 48.931832],
          [2.323222, 48.931452],
          [2.323464, 48.931223],
          [2.323791, 48.931043],
          [2.324504, 48.930690],
          [2.325116, 48.930465],
          [2.325422, 48.930454],
          [2.325459, 48.930588],
          [2.325389, 48.930690],
          [2.324874, 48.930690],
          [2.324016, 48.931082],
          [2.323394, 48.931490],
          [2.322954, 48.931882],
          [2.322814, 48.931843]
        ]
      ]
    }
  }, {
    "type": "Feature",
    "properties": {
      "SITEID": 25,
      "NOM": "VIEUX CHEMIN DE SAINT-DENIS",
      "message": "Lorem ipsum dolor sit amet, consectetur adipisicing elit."
    },
    "geometry": {
      "type": "Polygon",
      "coordinates": [
        [
          [2.322364, 48.931607],
          [2.323126, 48.931022],
          [2.324177, 48.930479],
          [2.325261, 48.930098],
          [2.326623, 48.929753],
          [2.327278, 48.929591],
          [2.328737, 48.929210],
          [2.329820, 48.928872],
          [2.330807, 48.928470],
          [2.331215, 48.928273],
          [2.331033, 48.928019],
          [2.329649, 48.928632],
          [2.328587, 48.928949],
          [2.327578, 48.929224],
          [2.326183, 48.929520],
          [2.325561, 48.929725],
          [2.324016, 48.930134],
          [2.323136, 48.930514],
          [2.322021, 48.931466],
          [2.322332, 48.931600]
        ]
      ]
    }
  }, {
    "type": "Feature",
    "properties": {
      "SITEID": 26,
      "NOM": "MADIESSE-LEDUDAL",
      "message": "Lorem ipsum dolor sit amet, consectetur adipisicing elit."
    },
    "geometry": {
      "type": "Polygon",
      "coordinates": [
        [
          [2.32699,48.93555],
          [2.32614,48.93538],
          [2.3264,48.93505],
          [2.32722,48.93514]
        ]
      ]
    }
  }, {
    "type": "Feature",
    "properties": {
      "SITEID": 27,
      "NOM": "QUAI SISLEY",
      "message": "Lorem ipsum dolor sit amet, consectetur adipisicing elit."
    },
    "geometry": {
      "type": "Polygon",
      "coordinates": [
        [
          [2.336070, 48.935732],
          [2.335770, 48.937247],
          [2.335700, 48.937691],
          [2.335635, 48.938219],
          [2.335593, 48.938817],
          [2.335453, 48.939335],
          [2.335233, 48.939854],
          [2.335029, 48.940337],
          [2.334820, 48.940666],
          [2.334369, 48.941164],
          [2.333999, 48.941458],
          [2.333554, 48.941787],
          [2.331955, 48.942769],
          [2.331065, 48.943292],
          [2.330995, 48.943217],
          [2.330979, 48.943137],
          [2.330958, 48.943073],
          [2.331258, 48.942938],
          [2.332658, 48.942146],
          [2.333114, 48.941852],
          [2.333812, 48.941378],
          [2.334021, 48.941199],
          [2.334294, 48.941010],
          [2.334471, 48.940820],
          [2.334734, 48.940536],
          [2.334938, 48.940143],
          [2.335035, 48.939879],
          [2.335303, 48.939141],
          [2.335533, 48.937502],
          [2.335641, 48.936824],
          [2.335737, 48.936415],
          [2.335770, 48.936071],
          [2.335834, 48.935867],
          [2.335855, 48.935792],
          [2.335904, 48.935742],
          [2.335952, 48.935742],
          [2.336006, 48.935732],
          [2.336059, 48.935732]
        ]
      ]
    }
  }, {
    "type": "Feature",
    "properties": {
      "SITEID": 28,
      "NOM": "QUAI D\"ASNIERES",
      "message": "Lorem ipsum dolor sit amet, consectetur adipisicing elit."
    },
    "geometry": {
      "type": "Polygon",
      "coordinates": [
        [
          [2.335845, 48.935523],
          [2.336129, 48.935553],
          [2.336167, 48.935119],
          [2.336193, 48.934830],
          [2.336199, 48.934706],
          [2.336199, 48.934601],
          [2.336086, 48.934023],
          [2.336011, 48.933594],
          [2.335952, 48.933430],
          [2.335882, 48.933116],
          [2.335807, 48.932946],
          [2.335040, 48.931217],
          [2.334117, 48.929478],
          [2.333565, 48.928396],
          [2.333447, 48.928481],
          [2.333490, 48.928790],
          [2.334144, 48.929856],
          [2.334895, 48.931242],
          [2.335834, 48.933375],
          [2.335952, 48.934347],
          [2.336016, 48.934696],
          [2.335936, 48.935194],
          [2.335845, 48.935508]
        ]
      ]
    }
  }, {
    "type": "Feature",
    "properties": {
      "SITEID": 29,
      "NOM": "CHANTIERS NAVALS",
      "message": "Lorem ipsum dolor sit amet, consectetur adipisicing elit."
    },
    "geometry": {
      "type": "Polygon",
      "coordinates": [
        [
          [2.32819, 48.94451],
          [2.32822, 48.94455],
          [2.32937 ,48.9442],
          [2.32919, 48.94402],
          [2.33001, 48.94379],
          [2.33063, 48.94336],
          [2.3306, 48.94334],
          [2.32996, 48.94376],
          [2.32905, 48.94401],
          [2.32922, 48.94421]
        ]
      ]
      }
  }, {
    "type": "Feature",
    "properties": {
        "SITEID": 30,
        "NOM": "PASSAGE DE LA MEF",
        "message": "Lorem ipsum dolor sit amet, consectetur adipisicing elit."
      },
      "geometry": {
        "type": "Polygon",
        "coordinates": [
          [
            [2.33576,48.93613],
            [2.33576,48.93617],
            [2.33547,48.93617],
            [2.33547,48.93613]
        ]
      ]
    }
  }, {
    "type": "Feature",
    "properties": {
      "SITEID": 31,
      "NOM": "PISCINE",
      "message": "Lorem ipsum dolor sit amet, consectetur adipisicing elit."
    },
    "geometry": {
      "type": "Polygon",
      "coordinates": [
        [
          [2.324,48.94188],
          [2.32457,48.94186],
          [2.32459,48.9418],
          [2.32449,48.9418],
          [2.32448,48.94184],
          [2.32401,48.94182],
          [2.32379,48.94173],
          [2.3237,48.94166],
          [2.32362,48.94158],
          [2.32364,48.9415],
          [2.32367,48.94138],
          [2.3237,48.94114],
          [2.32372,48.94104],
          [2.32312,48.94083],
          [2.32247,48.94116],
          [2.32244,48.94128],
          [2.32263,48.94143],
          [2.32289,48.94158],
          [2.32317,48.94169],
          [2.32347,48.94179],
          [2.32373,48.94185]
        ]
      ]
    }
  }, {
    "type": "Feature",
    "properties": {
      "SITEID": 32,
      "NOM": "RUE DU 8 MAI 1945",
      "message": "Lorem ipsum dolor sit amet, consectetur adipisicing elit."
    },
    "geometry": {
      "type": "MultiPolygon",
      "coordinates":
      [
        [
          [
            [2.31889,48.93806],
            [2.31893,48.93813],
            [2.31901,48.93818],
            [2.31908,48.93821],
            [2.3192,48.93823],
            [2.31922,48.93822],
            [2.31927,48.93821],
            [2.31934,48.9382],
            [2.31938,48.93817],
            [2.31944,48.93813],
            [2.31947,48.93809],
            [2.31948,48.93804],
            [2.3196,48.93803],
            [2.31971,48.93799],
            [2.32044,48.93756],
            [2.3209,48.9373],
            [2.32108,48.93724],
            [2.32125,48.9372],
            [2.32141,48.9372],
            [2.32239,48.93729],
            [2.32314,48.93733],
            [2.32423,48.93745],
            [2.32425,48.93737],
            [2.32393,48.93734],
            [2.32313,48.93725],
            [2.32143,48.93711],
            [2.32121,48.93711],
            [2.32103,48.93715],
            [2.32086,48.93722],
            [2.3207,48.93731],
            [2.3196,48.93792],
            [2.31947,48.93795],
            [2.31946,48.93791],
            [2.31939,48.93787],
            [2.31928,48.93784],
            [2.31916,48.93783],
            [2.31904,48.93786],
            [2.31895,48.93791],
            [2.3189,48.93798]
          ]
        ]
      ]
    }
  }, {
    "type": "Feature",
    "properties": {
      "SITEID": 33,
      "NOM": "BERTANE-BONGARDE",
      "message": "Lorem ipsum dolor sit amet, consectetur adipisicing elit."
    },
    "geometry": {
      "type":"MultiPolygon",
      "coordinates":
      [
        [
          [
            [2.3256,48.92487],
            [2.32569,48.92494],
            [2.32798,48.92338],
            [2.32788,48.92329]
          ]
        ]
      ]
    }
  }, {
    "type": "Feature",
    "properties": {
      "SITEID": 34,
      "NOM": "CHEMIN DU BÛCHER",
      "message": "Lorem ipsum dolor sit amet, consectetur adipisicing elit."
    },
    "geometry": {
      "type": "Polygon",
      "coordinates": [
        [
          [2.324456, 48.941939],
          [2.324520, 48.941480],
          [2.324563, 48.941262],
          [2.324628, 48.941142],
          [2.324713, 48.940994],
          [2.324746, 48.940860],
          [2.324756, 48.940684],
          [2.324703, 48.940557],
          [2.324735, 48.940134],
          [2.324703, 48.940092],
          [2.324778, 48.940015],
          [2.324842, 48.940008],
          [2.324917, 48.940127],
          [2.324971, 48.940332],
          [2.324971, 48.940748],
          [2.324971, 48.940860],
          [2.324885, 48.940987],
          [2.324853, 48.941128],
          [2.324660, 48.941931],
          [2.324606, 48.942023],
          [2.324499, 48.942002],
          [2.324480, 48.941996],
          [2.324461, 48.941942]
        ]
      ]
    }
  }]
}
